chedid/__init__.py
chedid/app_setup.py
chedid/apps.py
chedid/handlers/__init__.py
chedid/handlers/default_handler.py
chedid/handlers/jwt_handler.py
chedid/migrations/0001_initial.py
chedid/migrations/__init__.py
chedid/models/__init__.py
chedid/models/token_pair.py
chedid/utils/__init__.py
chedid/utils/verify_jwt.py
chedid/utils/verify_request.py
django_chedid-0.1.dist-info/LICENSE
django_chedid-0.1.dist-info/METADATA
django_chedid-0.1.dist-info/WHEEL
django_chedid-0.1.dist-info/top_level.txt
django_chedid-0.1.dist-info/RECORD
